counter/count.sv
`default_nettype none

/********************
 * Module
 ********************/

module counter
  (
   input   wire         clk_100m,
   input   wire         xreset,
   output  reg  [ 3: 0] count = 4'd0
   );

  always @(posedge clk_100m)  begin
    if (!xreset) begin
      count <= 4'd0;
    end
    else begin
      count <= count + 4'd1;
      //$monitor($time," : count=%d",count);
    end
  end

endmodule

counter/testbench.sv
`define CLK_100M 10000 //10000ps

`timescale 1ps/1ps

`default_nettype none

module testbench;
  //input
  reg         clk_100m;
  reg         xreset;
  //output
  wire [ 3: 0] count;

  initial begin
    clk_100m = 1'b1;
    xreset = 1'b0;
    #(`CLK_100M/2);
    xreset = 1'b1;
  end

  //CLK
  always #(`CLK_100M/2) begin
    clk_100m = ~clk_100m;
  end

  counter u_counter
    (
     .clk_100m,
     .xreset,
     .count
     );

  initial begin
    #100000 $finish();
  end

  initial begin
    $monitor($time," : count=%d",count);
    $dumpfile("counter_test.vcd");
    $dumpvars(0,u_counter);
  end

  integer        file;

  initial begin
    file=$fopen("test.csv","w+");
    $fdisplay(file,"1,2,3,4,5");
    $fclose(file);
  end
           
endmodule

counter/counter_test.vcd
$date
	Sun Sep 29 11:09:04 2019
$end
$version
	Icarus Verilog
$end
$timescale
	1ps
$end
$scope module testbench $end
$scope module u_counter $end
$var wire 1 ! clk_100m $end
$var wire 1 " xreset $end
$var reg 4 # count [3:0] $end
$upscope $end
$upscope $end
$enddefinitions $end
#0
$dumpvars
b0 #
0"
1!
$end
#5000
0!
1"
#10000
b1 #
1!
#15000
0!
#20000
b10 #
1!
#25000
0!
#30000
b11 #
1!
#35000
0!
#40000
b100 #
1!
#45000
0!
#50000
b101 #
1!
#55000
0!
#60000
b110 #
1!
#65000
0!
#70000
b111 #
1!
#75000
0!
#80000
b1000 #
1!
#85000
0!
#90000
b1001 #
1!
#95000
0!
#100000
b1010 #
1!
