education/udcnt200/udcnt200.sv
`default_nettype none

/***************************************************
 * Up Down Counter
 ***************************************************/

module udcnt200
  (
   input wire         rstx,
   input wire         clk,
   input wire	      upx,
   input wire	      ena,
   output reg [ 7: 0] q = 8'd0
   );

  always @(posedge clk) begin
    if (!rstx) begin
      q <= 8'd0;
    end
    else if (!ena) begin
      //NOP
    end
    else begin
      if(upx == 1'b0) begin
        if (q == 8'd199) begin
          q <= 8'd0;
        end
        else begin
          q <= q + 1'b1;
        end
      end
      else begin
        if (q == 8'd0) begin
          q <= 8'd199;
        end
        else begin
          q <= q - 1'b1;
        end
      end
    end
  end

endmodule

`default_nettype wire

education/udcnt200/tb_top.sv
`define CLK_100M 10000 //10000ps = 10ns
`timescale 1ps/1ps

`default_nettype none

/***************************************************
 * Testbench
 ***************************************************/

module testbench;
  reg          CLK;
  reg          XRST;
  reg	       UPX;
  reg	       COUNT_EN;
  wire [ 7: 0] Q;

// CLK
  always #(`CLK_100M/2) begin
    CLK = ~CLK;
  end

  udcnt200 u_udcnt200
    (
     .rstx ( XRST     ),
     .clk  ( CLK      ),
     .upx  ( UPX      ),
     .ena  ( COUNT_EN ),
     .q    ( Q        )
     );


  `include "testcase.inc"

  initial begin
    $dumpfile("udcnt200.vcd");
    $dumpvars(0,u_udcnt200);
  end
           
endmodule

education/udcnt200/udcnt200.vcd
$date
	Sun Jul  5 17:00:12 2020
$end
$version
	Icarus Verilog
$end
$timescale
	1ps
$end
$scope module testbench $end
$scope module u_udcnt200 $end
$var wire 1 ! clk $end
$var wire 1 " ena $end
$var wire 1 # rstx $end
$var wire 1 $ upx $end
$var reg 8 % q [7:0] $end
$upscope $end
$upscope $end
$enddefinitions $end
#0
$dumpvars
b0 %
0$
0#
1"
1!
$end
#5000
1#
0!
#10000
b1 %
1!
#15000
0!
#20000
b10 %
1!
#25000
0!
#30000
b11 %
1!
#35000
0!
#40000
b100 %
1!
#45000
0!
#50000
b101 %
1!
#55000
0!
#60000
b110 %
1!
#65000
0!
#70000
b111 %
1!
#75000
0!
#80000
b1000 %
1!
#85000
0!
#90000
b1001 %
1!
#95000
0!
#100000
b1010 %
1!
#105000
0!
#110000
b1011 %
1!
#115000
0!
#120000
b1100 %
1!
#125000
0!
#130000
b1101 %
1!
#135000
0!
#140000
b1110 %
1!
#145000
0!
#150000
b1111 %
1!
#155000
0!
#160000
b10000 %
1!
#165000
0!
#170000
b10001 %
1!
#175000
0!
#180000
b10010 %
1!
#185000
0!
#190000
b10011 %
1!
#195000
0!
#200000
b10100 %
1!
#205000
0!
#210000
b10101 %
1!
#215000
0!
#220000
b10110 %
1!
#225000
0!
#230000
b10111 %
1!
#235000
0!
#240000
b11000 %
1!
#245000
0!
#250000
b11001 %
1!
#255000
0!
#260000
b11010 %
1!
#265000
0!
#270000
b11011 %
1!
#275000
0!
#280000
b11100 %
1!
#285000
0!
#290000
b11101 %
1!
#295000
0!
#300000
b11110 %
1!
#305000
0!
#310000
b11111 %
1!
#315000
0!
#320000
b100000 %
1!
#325000
0!
#330000
b100001 %
1!
#335000
0!
#340000
b100010 %
1!
#345000
0!
#350000
b100011 %
1!
#355000
0!
#360000
b100100 %
1!
#365000
0!
#370000
b100101 %
1!
#375000
0!
#380000
b100110 %
1!
#385000
0!
#390000
b100111 %
1!
#395000
0!
#400000
b101000 %
1!
#405000
0!
#410000
b101001 %
1!
#415000
0!
#420000
b101010 %
1!
#425000
0!
#430000
b101011 %
1!
#435000
0!
#440000
b101100 %
1!
#445000
0!
#450000
b101101 %
1!
#455000
0!
#460000
b101110 %
1!
#465000
0!
#470000
b101111 %
1!
#475000
0!
#480000
b110000 %
1!
#485000
0!
#490000
b110001 %
1!
#495000
0!
#500000
b110010 %
1!
#505000
0!
#510000
b110011 %
1!
#515000
0!
#520000
b110100 %
1!
#525000
0!
#530000
b110101 %
1!
#535000
0!
#540000
b110110 %
1!
#545000
0!
#550000
b110111 %
1!
#555000
0!
#560000
b111000 %
1!
#565000
0!
#570000
b111001 %
1!
#575000
0!
#580000
b111010 %
1!
#585000
0!
#590000
b111011 %
1!
#595000
0!
#600000
b111100 %
1!
#605000
0!
#610000
b111101 %
1!
#615000
0!
#620000
b111110 %
1!
#625000
0!
#630000
b111111 %
1!
#635000
0!
#640000
b1000000 %
1!
#645000
0!
#650000
b1000001 %
1!
#655000
0!
#660000
b1000010 %
1!
#665000
0!
#670000
b1000011 %
1!
#675000
0!
#680000
b1000100 %
1!
#685000
0!
#690000
b1000101 %
1!
#695000
0!
#700000
b1000110 %
1!
#705000
0!
#710000
b1000111 %
1!
#715000
0!
#720000
b1001000 %
1!
#725000
0!
#730000
b1001001 %
1!
#735000
0!
#740000
b1001010 %
1!
#745000
0!
#750000
b1001011 %
1!
#755000
0!
#760000
b1001100 %
1!
#765000
0!
#770000
b1001101 %
1!
#775000
0!
#780000
b1001110 %
1!
#785000
0!
#790000
b1001111 %
1!
#795000
0!
#800000
b1010000 %
1!
#805000
0!
#810000
b1010001 %
1!
#815000
0!
#820000
b1010010 %
1!
#825000
0!
#830000
b1010011 %
1!
#835000
0!
#840000
b1010100 %
1!
#845000
0!
#850000
b1010101 %
1!
#855000
0!
#860000
b1010110 %
1!
#865000
0!
#870000
b1010111 %
1!
#875000
0!
#880000
b1011000 %
1!
#885000
0!
#890000
b1011001 %
1!
#895000
0!
#900000
b1011010 %
1!
#905000
0!
#910000
b1011011 %
1!
#915000
0!
#920000
b1011100 %
1!
#925000
0!
#930000
b1011101 %
1!
#935000
0!
#940000
b1011110 %
1!
#945000
0!
#950000
b1011111 %
1!
#955000
0!
#960000
b1100000 %
1!
#965000
0!
#970000
b1100001 %
1!
#975000
0!
#980000
b1100010 %
1!
#985000
0!
#990000
b1100011 %
1!
#995000
0!
#1000000
b1100100 %
1!
#1005000
0!
0"
